[
    {
        "id":1,
        "name": "VISA CAL - Natalia",
        "balance": -17227.3,
        "currency": "ils",
        "currencySymbol": "?",
        "icon": "ion-card",
        "color":"balanced",
        "lastValidated": "2014-07-08 12:30"
    },
    {
        "id":2,
        "name": "Cash",
        "balance": 324,
        "currency": "ils",
        "currencySymbol": "?",
        "icon": "ion-cash",
        "lastValidated": "2016-01-08 12:30"
    },
    {
        "id":3,
        "name": "Bank",
        "balance": -147,
        "currency": "ils",
        "currencySymbol": "?",
        "icon": "ion-card",
        "lastValidated": "2014-07-08 12:30"
    }
]
